flake8_linenumber.py
flake8_linenumber-0.1.8.dist-info/LICENSE
flake8_linenumber-0.1.8.dist-info/METADATA
flake8_linenumber-0.1.8.dist-info/WHEEL
flake8_linenumber-0.1.8.dist-info/entry_points.txt
flake8_linenumber-0.1.8.dist-info/top_level.txt
flake8_linenumber-0.1.8.dist-info/RECORD
