Metadata-Version: 2.1
Name: flake8-linenumber
Version: 0.1.8
Summary: flake8 plugin to limit line number in a module
Home-page: https://github.com/brabadu/flake8-linenumber
Author: Boryslav Larin
Author-email: brabadu@gmail.com
License: MIT
Platform: UNKNOWN
Classifier: Framework :: Flake8
Classifier: Environment :: Console
Classifier: Intended Audience :: Developers
Classifier: License :: OSI Approved :: MIT License
Classifier: Programming Language :: Python
Classifier: Programming Language :: Python :: 3
Classifier: Topic :: Software Development :: Libraries :: Python Modules
Classifier: Topic :: Software Development :: Quality Assurance
Requires-Dist: flake8 (>3.0.0)
